validify/__init__.py
validify/validify.py
validify/helpers/__init__.py
validify/helpers/cleanup_compare_strings.py
validify/helpers/messages.py
validify/helpers/normalize_space.py
validify/tests/__init__.py
validify/tests/prepare_testdata.py
validify/tests/test_main.py
validify-0.0.15.dist-info/LICENSE
validify-0.0.15.dist-info/METADATA
validify-0.0.15.dist-info/WHEEL
validify-0.0.15.dist-info/top_level.txt
validify-0.0.15.dist-info/RECORD
