Metadata-Version: 2.1
Name: validify
Version: 0.0.15
Summary: validify is a rule-based validation module for assessing the structure of an xml tree, built on top of the lxml library. It currently covers a subset of the XML Schema 1.1 Definition.
Home-page: https://github.com/olivergoetze/validify
Author: Oliver Götze
Author-email: oliver.goetze@mailbox.org
License: MIT
Platform: UNKNOWN
Classifier: Development Status :: 3 - Alpha
Classifier: License :: OSI Approved :: MIT License
Classifier: Programming Language :: Python
Classifier: Programming Language :: Python :: 3.5
Classifier: Programming Language :: Python :: 3.6
Classifier: Programming Language :: Python :: 3.7
Classifier: Programming Language :: Python :: 3.8
Classifier: Topic :: Software Development :: Libraries
Classifier: Topic :: Software Development :: Libraries :: Python Modules
Classifier: Intended Audience :: Developers
Requires-Python: >=3.5
Requires-Dist: lxml
Requires-Dist: loguru
